MANIFEST.in
README.rst
setup.py
aliyun_python_sdk_hpc.egg-info/PKG-INFO
aliyun_python_sdk_hpc.egg-info/SOURCES.txt
aliyun_python_sdk_hpc.egg-info/dependency_links.txt
aliyun_python_sdk_hpc.egg-info/requires.txt
aliyun_python_sdk_hpc.egg-info/top_level.txt
aliyunsdkhpc/__init__.py
aliyunsdkhpc/request/__init__.py
aliyunsdkhpc/request/v20160603/CreateInstanceRequest.py
aliyunsdkhpc/request/v20160603/DeleteInstanceRequest.py
aliyunsdkhpc/request/v20160603/DescribeInstancesRequest.py
aliyunsdkhpc/request/v20160603/ModifyJumpserverPasswordRequest.py
aliyunsdkhpc/request/v20160603/RebootInstanceRequest.py
aliyunsdkhpc/request/v20160603/RebootJumpserverRequest.py
aliyunsdkhpc/request/v20160603/StartJumpserverRequest.py
aliyunsdkhpc/request/v20160603/StopJumpserverRequest.py
aliyunsdkhpc/request/v20160603/__init__.py
aliyunsdkhpc/request/v20161213/AuthorizeSecurityGroupRequest.py
aliyunsdkhpc/request/v20161213/DescribeInstancesInSecurityGroupRequest.py
aliyunsdkhpc/request/v20161213/DescribeInstancesRequest.py
aliyunsdkhpc/request/v20161213/DescribeSecurityGroupAttributeRequest.py
aliyunsdkhpc/request/v20161213/ModifyInstancePasswordRequest.py
aliyunsdkhpc/request/v20161213/ModifyJumpserverPasswordRequest.py
aliyunsdkhpc/request/v20161213/RebootInstanceRequest.py
aliyunsdkhpc/request/v20161213/RebootJumpserverRequest.py
aliyunsdkhpc/request/v20161213/RevokeSecurityGroupRequest.py
aliyunsdkhpc/request/v20161213/StartJumpserverRequest.py
aliyunsdkhpc/request/v20161213/StopJumpserverRequest.py
aliyunsdkhpc/request/v20161213/__init__.py